cli/__init__.py
cli/cli.py
cli/cli_pg_server_config_subparser.py
cli/cli_pgconfig_subparser.py
cli/cli_settings_subparser.py
cli/cli_toplevel_parser.py
pglinker/__init__.py
pglinker/common/__init__.py
pglinker/common/config/__init__.py
pglinker/common/templates/postgres.yaml
pglinker/common/utils/__init__.py
pglinker/common/utils/pathutils.py
pglinker/connections/__init__.py
pglinker/connections/base.py
pglinker/connections/postgres/__init__.py
pglinker/connections/postgres/async_connection.py
pglinker/connections/postgres/async_pool_connection.py
pglinker/connections/postgres/base_connection.py
pglinker/connections/postgres/normal_connection.py
pglinker/connections/postgres/pool_connection.py
pglinker/connections/postgres/postgres_connection_factory.py
pglinker/managers/__init__.py
pglinker/managers/pg_server_config_manager.py
pglinker/managers/pgconfig_manager.py
pglinker/managers/pgconnection_manager.py
pglinker/managers/settings_manager.py
pglinker/managers/toplevel_manager.py
pglinker/serversettings/postgres_server_config_generator.py
tests/__init__.py
tests/database_integration_test.py
pglinker-0.0.2.dist-info/LICENSE
pglinker-0.0.2.dist-info/METADATA
pglinker-0.0.2.dist-info/WHEEL
pglinker-0.0.2.dist-info/entry_points.txt
pglinker-0.0.2.dist-info/top_level.txt
pglinker-0.0.2.dist-info/RECORD
