Metadata-Version: 2.1
Name: pglinker
Version: 0.0.2
Summary: A tool to assist with database connections and manage data.
Author-email: Good Boy <pythonic@rexbytes.com>
License: MIT License
Project-URL: Homepage, https://github.com/RexBytes/pglinker
Project-URL: Bug Tracker, https://github.com/RexBytes/pglinker
Classifier: Programming Language :: Python :: 3.12
Classifier: License :: OSI Approved :: MIT License
Classifier: Operating System :: OS Independent
Classifier: Topic :: Database
Classifier: Topic :: Software Development :: Libraries :: Python Modules
Requires-Python: >=3.12
License-File: LICENSE
Requires-Dist: psycopg[binary] >=3.2.1
Requires-Dist: psycopg-pool >=3.2.2
Requires-Dist: PyYAML >=6.0.2
